{
    "location": {
        "name": "Madikeri",
        "region": "Karnataka",
        "country": "India",
        "lat": 12.42,
        "lon": 75.73,
        "tz_id": "Asia/Kolkata",
        "localtime_epoch": 1711011713,
        "localtime": "2024-03-21 14:31"
    },
    "current": {
        "last_updated_epoch": 1711011600,
        "last_updated": "2024-03-21 14:30",
        "temp_c": 35.5,
        "temp_f": 95.8,
        "is_day": 1,
        "condition": {
            "text": "Sunny",
            "icon": "//cdn.weatherapi.com/weather/64x64/day/113.png",
            "code": 1000
        },
        "wind_mph": 2.7,
        "wind_kph": 4.3,
        "wind_degree": 105,
        "wind_dir": "ESE",
        "pressure_mb": 1008,
        "pressure_in": 29.76,
        "precip_mm": 0,
        "precip_in": 0,
        "humidity": 25,
        "cloud": 11,
        "feelslike_c": 34.8,
        "feelslike_f": 94.7,
        "vis_km": 10,
        "vis_miles": 6,
        "uv": 9,
        "gust_mph": 3.1,
        "gust_kph": 5
    },
    "forecast": {
        "forecastday": [
            {
                "date": "2024-03-21",
                "date_epoch": 1710979200,
                "day": {
                    "maxtemp_c": 35.5,
                    "maxtemp_f": 95.8,
                    "mintemp_c": 17.5,
                    "mintemp_f": 63.6,
                    "avgtemp_c": 24.4,
                    "avgtemp_f": 76,
                    "maxwind_mph": 4.9,
                    "maxwind_kph": 7.9,
                    "totalprecip_mm": 0.91,
                    "totalprecip_in": 0.04,
                    "totalsnow_cm": 0,
                    "avgvis_km": 8.7,
                    "avgvis_miles": 5,
                    "avghumidity": 68,
                    "daily_will_it_rain": 1,
                    "daily_chance_of_rain": 86,
                    "daily_will_it_snow": 0,
                    "daily_chance_of_snow": 0,
                    "condition": {
                        "text": "Patchy rain nearby",
                        "icon": "//cdn.weatherapi.com/weather/64x64/day/176.png",
                        "code": 1063
                    },
                    "uv": 11
                },
                "astro": {
                    "sunrise": "06:30 AM",
                    "sunset": "06:38 PM",
                    "moonrise": "03:46 PM",
                    "moonset": "04:00 AM",
                    "moon_phase": "Waxing Gibbous",
                    "moon_illumination": 84,
                    "is_moon_up": 0,
                    "is_sun_up": 0
                },
                "hour": [
                    {
                        "condition": {},
                        "short_rad": 0,
                        "diff_rad": 0
                    },
                    {
                        "condition": {},
                        "short_rad": 0,
                        "diff_rad": 0
                    },
                    {
                        "condition": {},
                        "short_rad": 0,
                        "diff_rad": 0
                    },
                    {
                        "condition": {},
                        "short_rad": 0,
                        "diff_rad": 0
                    },
                    {
                        "condition": {},
                        "short_rad": 0,
                        "diff_rad": 0
                    },
                    {
                        "condition": {},
                        "short_rad": 0,
                        "diff_rad": 0
                    },
                    {
                        "condition": {},
                        "short_rad": 0,
                        "diff_rad": 0
                    },
                    {
                        "condition": {},
                        "short_rad": 36.2,
                        "diff_rad": 12.77
                    },
                    {
                        "condition": {},
                        "short_rad": 131.18,
                        "diff_rad": 28.18
                    },
                    {
                        "condition": {},
                        "short_rad": 241.78,
                        "diff_rad": 39.99
                    },
                    {
                        "condition": {},
                        "short_rad": 350.37,
                        "diff_rad": 52.34
                    },
                    {
                        "condition": {},
                        "short_rad": 449.66,
                        "diff_rad": 58
                    },
                    {
                        "condition": {},
                        "short_rad": 1033.52,
                        "diff_rad": 83.55
                    },
                    {
                        "condition": {},
                        "short_rad": 1026.24,
                        "diff_rad": 110.15
                    },
                    {
                        "condition": {},
                        "short_rad": 957.36,
                        "diff_rad": 121.14
                    },
                    {
                        "condition": {},
                        "short_rad": 910.1,
                        "diff_rad": 129.46
                    },
                    {
                        "condition": {},
                        "short_rad": 848.94,
                        "diff_rad": 119.99
                    },
                    {
                        "condition": {},
                        "short_rad": 754.32,
                        "diff_rad": 115.06
                    },
                    {
                        "condition": {},
                        "short_rad": 76.6,
                        "diff_rad": 29.46
                    },
                    {
                        "condition": {},
                        "short_rad": 38.42,
                        "diff_rad": 14.79
                    },
                    {
                        "condition": {},
                        "short_rad": 25.62,
                        "diff_rad": 9.86
                    },
                    {
                        "condition": {},
                        "short_rad": 19.2,
                        "diff_rad": 7.4
                    },
                    {
                        "condition": {},
                        "short_rad": 15.36,
                        "diff_rad": 5.92
                    },
                    {
                        "condition": {},
                        "short_rad": 12.8,
                        "diff_rad": 4.93
                    }
                ]
            },
            {
                "date": "2024-03-22",
                "date_epoch": 1711065600,
                "day": {
                    "maxtemp_c": 36.9,
                    "maxtemp_f": 98.4,
                    "mintemp_c": 17.5,
                    "mintemp_f": 63.5,
                    "avgtemp_c": 25.2,
                    "avgtemp_f": 77.3,
                    "maxwind_mph": 6.3,
                    "maxwind_kph": 10.1,
                    "totalprecip_mm": 0.79,
                    "totalprecip_in": 0.03,
                    "totalsnow_cm": 0,
                    "avgvis_km": 6.7,
                    "avgvis_miles": 4,
                    "avghumidity": 73,
                    "daily_will_it_rain": 1,
                    "daily_chance_of_rain": 81,
                    "daily_will_it_snow": 0,
                    "daily_chance_of_snow": 0,
                    "condition": {
                        "text": "Patchy rain nearby",
                        "icon": "//cdn.weatherapi.com/weather/64x64/day/176.png",
                        "code": 1063
                    },
                    "uv": 11
                },
                "astro": {
                    "sunrise": "06:30 AM",
                    "sunset": "06:38 PM",
                    "moonrise": "04:33 PM",
                    "moonset": "04:40 AM",
                    "moon_phase": "Waxing Gibbous",
                    "moon_illumination": 91,
                    "is_moon_up": 0,
                    "is_sun_up": 0
                },
                "hour": [
                    {
                        "condition": {},
                        "short_rad": 0,
                        "diff_rad": 0
                    },
                    {
                        "condition": {},
                        "short_rad": 0,
                        "diff_rad": 0
                    },
                    {
                        "condition": {},
                        "short_rad": 0,
                        "diff_rad": 0
                    },
                    {
                        "condition": {},
                        "short_rad": 0,
                        "diff_rad": 0
                    },
                    {
                        "condition": {},
                        "short_rad": 0,
                        "diff_rad": 0
                    },
                    {
                        "condition": {},
                        "short_rad": 0,
                        "diff_rad": 0
                    },
                    {
                        "condition": {},
                        "short_rad": 0,
                        "diff_rad": 0
                    },
                    {
                        "condition": {},
                        "short_rad": 36.58,
                        "diff_rad": 13.22
                    },
                    {
                        "condition": {},
                        "short_rad": 132.02,
                        "diff_rad": 29.03
                    },
                    {
                        "condition": {},
                        "short_rad": 243.14,
                        "diff_rad": 40.62
                    },
                    {
                        "condition": {},
                        "short_rad": 352.96,
                        "diff_rad": 49.03
                    },
                    {
                        "condition": {},
                        "short_rad": 451.89,
                        "diff_rad": 55.73
                    },
                    {
                        "condition": {},
                        "short_rad": 929.46,
                        "diff_rad": 144.62
                    },
                    {
                        "condition": {},
                        "short_rad": 842.42,
                        "diff_rad": 130.03
                    },
                    {
                        "condition": {},
                        "short_rad": 656.96,
                        "diff_rad": 138.61
                    },
                    {
                        "condition": {},
                        "short_rad": 599.6,
                        "diff_rad": 141.96
                    },
                    {
                        "condition": {},
                        "short_rad": 534.6,
                        "diff_rad": 129.26
                    },
                    {
                        "condition": {},
                        "short_rad": 471.42,
                        "diff_rad": 119.5
                    },
                    {
                        "condition": {},
                        "short_rad": 100.14,
                        "diff_rad": 33.91
                    },
                    {
                        "condition": {},
                        "short_rad": 50.2,
                        "diff_rad": 17.02
                    },
                    {
                        "condition": {},
                        "short_rad": 33.46,
                        "diff_rad": 11.34
                    },
                    {
                        "condition": {},
                        "short_rad": 25.1,
                        "diff_rad": 8.51
                    },
                    {
                        "condition": {},
                        "short_rad": 20.08,
                        "diff_rad": 6.81
                    },
                    {
                        "condition": {},
                        "short_rad": 16.74,
                        "diff_rad": 5.67
                    }
                ]
            },
            {
                "date": "2024-03-23",
                "date_epoch": 1711152000,
                "day": {
                    "maxtemp_c": 33.8,
                    "maxtemp_f": 92.8,
                    "mintemp_c": 17.3,
                    "mintemp_f": 63.1,
                    "avgtemp_c": 23.5,
                    "avgtemp_f": 74.3,
                    "maxwind_mph": 6.7,
                    "maxwind_kph": 10.8,
                    "totalprecip_mm": 0.02,
                    "totalprecip_in": 0,
                    "totalsnow_cm": 0,
                    "avgvis_km": 8.1,
                    "avgvis_miles": 5,
                    "avghumidity": 70,
                    "daily_will_it_rain": 0,
                    "daily_chance_of_rain": 0,
                    "daily_will_it_snow": 0,
                    "daily_chance_of_snow": 0,
                    "condition": {
                        "text": "Partly Cloudy ",
                        "icon": "//cdn.weatherapi.com/weather/64x64/day/116.png",
                        "code": 1003
                    },
                    "uv": 11
                },
                "astro": {
                    "sunrise": "06:29 AM",
                    "sunset": "06:38 PM",
                    "moonrise": "05:19 PM",
                    "moonset": "05:16 AM",
                    "moon_phase": "Waxing Gibbous",
                    "moon_illumination": 95,
                    "is_moon_up": 0,
                    "is_sun_up": 0
                },
                "hour": [
                    {
                        "condition": {},
                        "short_rad": 0,
                        "diff_rad": 0
                    },
                    {
                        "condition": {},
                        "short_rad": 0,
                        "diff_rad": 0
                    },
                    {
                        "condition": {},
                        "short_rad": 0,
                        "diff_rad": 0
                    },
                    {
                        "condition": {},
                        "short_rad": 0,
                        "diff_rad": 0
                    },
                    {
                        "condition": {},
                        "short_rad": 0,
                        "diff_rad": 0
                    },
                    {
                        "condition": {},
                        "short_rad": 0,
                        "diff_rad": 0
                    },
                    {
                        "condition": {},
                        "short_rad": 0,
                        "diff_rad": 0
                    },
                    {
                        "condition": {},
                        "short_rad": 37.76,
                        "diff_rad": 13.22
                    },
                    {
                        "condition": {},
                        "short_rad": 133.44,
                        "diff_rad": 28.34
                    },
                    {
                        "condition": {},
                        "short_rad": 244.3,
                        "diff_rad": 39.42
                    },
                    {
                        "condition": {},
                        "short_rad": 353.79,
                        "diff_rad": 47.5
                    },
                    {
                        "condition": {},
                        "short_rad": 452.67,
                        "diff_rad": 53.61
                    },
                    {
                        "condition": {},
                        "short_rad": 999.96,
                        "diff_rad": 188.38
                    },
                    {
                        "condition": {},
                        "short_rad": 579.2,
                        "diff_rad": 144.5
                    },
                    {
                        "condition": {},
                        "short_rad": 407.28,
                        "diff_rad": 111.32
                    },
                    {
                        "condition": {},
                        "short_rad": 380.02,
                        "diff_rad": 124.94
                    },
                    {
                        "condition": {},
                        "short_rad": 349.41,
                        "diff_rad": 123.66
                    },
                    {
                        "condition": {},
                        "short_rad": 349.95,
                        "diff_rad": 113.31
                    },
                    {
                        "condition": {},
                        "short_rad": 101.24,
                        "diff_rad": 32.79
                    },
                    {
                        "condition": {},
                        "short_rad": 50.74,
                        "diff_rad": 16.45
                    },
                    {
                        "condition": {},
                        "short_rad": 33.82,
                        "diff_rad": 10.97
                    },
                    {
                        "condition": {},
                        "short_rad": 25.36,
                        "diff_rad": 8.22
                    },
                    {
                        "condition": {},
                        "short_rad": 20.29,
                        "diff_rad": 6.58
                    },
                    {
                        "condition": {},
                        "short_rad": 16.91,
                        "diff_rad": 5.48
                    }
                ]
            }
        ]
    }
}